athanor/__init__.py
athanor/app.py
athanor/launcher.py
athanor/shared.py
athanor/startup.py
athanor/utils.py
athanor-0.1.0.data/scripts/athanor
athanor_portal/__init__.py
athanor_portal/app.py
athanor_portal/config.py
athanor_portal/conn.py
athanor_portal/link.py
athanor_portal/net.py
athanor_portal/telnet.py
athanor_portal/websocket.py
athanor_server/__init__.py
athanor_server/app.py
athanor_server/config.py
athanor_server/conn.py
athanor_server/link.py
athanor-0.1.0.dist-info/LICENSE.txt
athanor-0.1.0.dist-info/METADATA
athanor-0.1.0.dist-info/WHEEL
athanor-0.1.0.dist-info/top_level.txt
athanor-0.1.0.dist-info/RECORD
