Metadata-Version: 2.1
Name: athanor
Version: 0.1.0
Summary: UNKNOWN
Home-page: https://github.com/volundmush/athanor
Author: Volund
Maintainer: Volund
License: MIT
Project-URL: Source, https://github.com/volundmush/athanor
Project-URL: Issue tracker, https://github.com/volundmush/athanor/issues
Project-URL: Patreon, https://www.patreon.com/volund
Platform: UNKNOWN
Classifier: Programming Language :: Python :: 3 :: Only
Classifier: Programming Language :: Python :: 3.8
Classifier: Intended Audience :: Developers
Classifier: Topic :: Games/Entertainment :: Multi-User Dungeons (MUD)
Classifier: Topic :: Games/Entertainment :: Puzzle Games
Classifier: Topic :: Games/Entertainment :: Role-Playing
Classifier: Topic :: Games/Entertainment :: Simulation
Classifier: Topic :: Software Development :: Libraries :: Application Frameworks
Requires-Python: >=3.8
License-File: LICENSE.txt
Requires-Dist: mudtelnet
Requires-Dist: setproctitle
Requires-Dist: websockets
Requires-Dist: uvloop
Requires-Dist: dataclasses-json
Requires-Dist: orjson
